<?xml version="1.0" encoding="UTF-8"?>
<edgarSubmission xmlns:ns1="http://www.sec.gov/edgar/common" xmlns="http://www.sec.gov/edgar/thirteenffiler">
  <schemaVersion>X0202</schemaVersion>
  <headerData>
    <submissionType>13F-HR</submissionType>
    <filerInfo>
      <liveTestFlag>LIVE</liveTestFlag>
      <flags>
        <confirmingCopyFlag>false</confirmingCopyFlag>
        <returnCopyFlag>false</returnCopyFlag>
        <overrideInternetFlag>false</overrideInternetFlag>
      </flags>
      <filer>
        <credentials>
          <cik>0001040273</cik>
          <ccc>XXXXXXXX</ccc>
        </credentials>
      </filer>
      <periodOfReport>09-30-2025</periodOfReport>
    </filerInfo>
  </headerData>
  <formData>
    <coverPage>
      <reportCalendarOrQuarter>09-30-2025</reportCalendarOrQuarter>
      <isAmendment>false</isAmendment>
      <filingManager>
        <name>Third Point LLC</name>
        <address>
          <ns1:street1>55 HUDSON YARDS</ns1:street1>
          <ns1:city>NEW YORK</ns1:city>
          <ns1:stateOrCountry>NY</ns1:stateOrCountry>
          <ns1:zipCode>10001</ns1:zipCode>
        </address>
      </filingManager>
      <reportType>13F HOLDINGS REPORT</reportType>
      <form13FFileNumber>028-06970</form13FFileNumber>
      <crdNumber>000137927</crdNumber>
      <secFileNumber>801-65088</secFileNumber>
      <provideInfoForInstruction5>N</provideInfoForInstruction5>
    </coverPage>
    <signatureBlock>
      <name>Daniel S. Loeb</name>
      <title>CEO</title>
      <phone>212-715-3880</phone>
      <signature>/s/  Daniel S. Loeb</signature>
      <city>New York</city>
      <stateOrCountry>NY</stateOrCountry>
      <signatureDate>11-14-2025</signatureDate>
    </signatureBlock>
    <summaryPage>
      <otherIncludedManagersCount>0</otherIncludedManagersCount>
      <tableEntryTotal>46</tableEntryTotal>
      <tableValueTotal>8989033614</tableValueTotal>
      <isConfidentialOmitted>false</isConfidentialOmitted>
    </summaryPage>
  </formData>
</edgarSubmission>
