<?xml version="1.0" encoding="UTF-8" standalone="yes"?>
<ns4:informationTable xmlns:ns4="http://www.sec.gov/edgar/document/thirteenf/informationtable">
	<ns4:infoTable>
		<ns4:nameOfIssuer>ALPHABET INC</ns4:nameOfIssuer>
		<ns4:titleOfClass>CAP STK CL C</ns4:titleOfClass>
		<ns4:cusip>02079K107</ns4:cusip>
		<ns4:value>452550</ns4:value>
		<ns4:shrsOrPrnAmt>
			<ns4:sshPrnamt>1858138</ns4:sshPrnamt>
			<ns4:sshPrnamtType>SH</ns4:sshPrnamtType>
		</ns4:shrsOrPrnAmt>
		<ns4:investmentDiscretion>SOLE</ns4:investmentDiscretion>
		<ns4:votingAuthority>
			<ns4:Sole>1858138</ns4:Sole>
			<ns4:Shared>0</ns4:Shared>
			<ns4:None>0</ns4:None>
		</ns4:votingAuthority>
	</ns4:infoTable>
	<ns4:infoTable>
		<ns4:nameOfIssuer>AMERICOLD REALTY TRUST INC</ns4:nameOfIssuer>
		<ns4:titleOfClass>COM</ns4:titleOfClass>
		<ns4:cusip>03064D108</ns4:cusip>
		<ns4:value>44064</ns4:value>
		<ns4:shrsOrPrnAmt>
			<ns4:sshPrnamt>3600000</ns4:sshPrnamt>
			<ns4:sshPrnamtType>SH</ns4:sshPrnamtType>
		</ns4:shrsOrPrnAmt>
		<ns4:investmentDiscretion>SOLE</ns4:investmentDiscretion>
		<ns4:votingAuthority>
			<ns4:Sole>3600000</ns4:Sole>
			<ns4:Shared>0</ns4:Shared>
			<ns4:None>0</ns4:None>
		</ns4:votingAuthority>
	</ns4:infoTable>
	<ns4:infoTable>
		<ns4:nameOfIssuer>CABLE ONE INC</ns4:nameOfIssuer>
		<ns4:titleOfClass>NOTE 1.125% 3/1</ns4:titleOfClass>
		<ns4:cusip>12685JAG0</ns4:cusip>
		<ns4:value>12068</ns4:value>
		<ns4:shrsOrPrnAmt>
			<ns4:sshPrnamt>14100000</ns4:sshPrnamt>
			<ns4:sshPrnamtType>PRN</ns4:sshPrnamtType>
		</ns4:shrsOrPrnAmt>
		<ns4:investmentDiscretion>SOLE</ns4:investmentDiscretion>
		<ns4:votingAuthority>
			<ns4:Sole>14100000</ns4:Sole>
			<ns4:Shared>0</ns4:Shared>
			<ns4:None>0</ns4:None>
		</ns4:votingAuthority>
	</ns4:infoTable>
	<ns4:infoTable>
		<ns4:nameOfIssuer>CRH PLC</ns4:nameOfIssuer>
		<ns4:titleOfClass>ORD</ns4:titleOfClass>
		<ns4:cusip>G25508105</ns4:cusip>
		<ns4:value>405669</ns4:value>
		<ns4:shrsOrPrnAmt>
			<ns4:sshPrnamt>3383395</ns4:sshPrnamt>
			<ns4:sshPrnamtType>SH</ns4:sshPrnamtType>
		</ns4:shrsOrPrnAmt>
		<ns4:investmentDiscretion>SOLE</ns4:investmentDiscretion>
		<ns4:votingAuthority>
			<ns4:Sole>3383395</ns4:Sole>
			<ns4:Shared>0</ns4:Shared>
			<ns4:None>0</ns4:None>
		</ns4:votingAuthority>
	</ns4:infoTable>
	<ns4:infoTable>
		<ns4:nameOfIssuer>DOLLAR GEN CORP NEW</ns4:nameOfIssuer>
		<ns4:titleOfClass>COM</ns4:titleOfClass>
		<ns4:cusip>256677105</ns4:cusip>
		<ns4:value>275622</ns4:value>
		<ns4:shrsOrPrnAmt>
			<ns4:sshPrnamt>2666876</ns4:sshPrnamt>
			<ns4:sshPrnamtType>SH</ns4:sshPrnamtType>
		</ns4:shrsOrPrnAmt>
		<ns4:investmentDiscretion>SOLE</ns4:investmentDiscretion>
		<ns4:votingAuthority>
			<ns4:Sole>2666876</ns4:Sole>
			<ns4:Shared>0</ns4:Shared>
			<ns4:None>0</ns4:None>
		</ns4:votingAuthority>
	</ns4:infoTable>
	<ns4:infoTable>
		<ns4:nameOfIssuer>EAGLE MATLS INC</ns4:nameOfIssuer>
		<ns4:titleOfClass>COM</ns4:titleOfClass>
		<ns4:cusip>26969P108</ns4:cusip>
		<ns4:value>218978</ns4:value>
		<ns4:shrsOrPrnAmt>
			<ns4:sshPrnamt>939660</ns4:sshPrnamt>
			<ns4:sshPrnamtType>SH</ns4:sshPrnamtType>
		</ns4:shrsOrPrnAmt>
		<ns4:investmentDiscretion>SOLE</ns4:investmentDiscretion>
		<ns4:votingAuthority>
			<ns4:Sole>939660</ns4:Sole>
			<ns4:Shared>0</ns4:Shared>
			<ns4:None>0</ns4:None>
		</ns4:votingAuthority>
	</ns4:infoTable>
	<ns4:infoTable>
		<ns4:nameOfIssuer>ELEVANCE HEALTH INC FORMERLY</ns4:nameOfIssuer>
		<ns4:titleOfClass>COM</ns4:titleOfClass>
		<ns4:cusip>036752103</ns4:cusip>
		<ns4:value>426195</ns4:value>
		<ns4:shrsOrPrnAmt>
			<ns4:sshPrnamt>1319000</ns4:sshPrnamt>
			<ns4:sshPrnamtType>SH</ns4:sshPrnamtType>
		</ns4:shrsOrPrnAmt>
		<ns4:investmentDiscretion>SOLE</ns4:investmentDiscretion>
		<ns4:votingAuthority>
			<ns4:Sole>1319000</ns4:Sole>
			<ns4:Shared>0</ns4:Shared>
			<ns4:None>0</ns4:None>
		</ns4:votingAuthority>
	</ns4:infoTable>
	<ns4:infoTable>
		<ns4:nameOfIssuer>FERGUSON ENTERPRISES INC</ns4:nameOfIssuer>
		<ns4:titleOfClass>COMMON STOCK NEW</ns4:titleOfClass>
		<ns4:cusip>31488V107</ns4:cusip>
		<ns4:value>259502</ns4:value>
		<ns4:shrsOrPrnAmt>
			<ns4:sshPrnamt>1155500</ns4:sshPrnamt>
			<ns4:sshPrnamtType>SH</ns4:sshPrnamtType>
		</ns4:shrsOrPrnAmt>
		<ns4:investmentDiscretion>SOLE</ns4:investmentDiscretion>
		<ns4:votingAuthority>
			<ns4:Sole>1155500</ns4:Sole>
			<ns4:Shared>0</ns4:Shared>
			<ns4:None>0</ns4:None>
		</ns4:votingAuthority>
	</ns4:infoTable>
	<ns4:infoTable>
		<ns4:nameOfIssuer>FIDELITY NATL INFORMATION SV</ns4:nameOfIssuer>
		<ns4:titleOfClass>COM</ns4:titleOfClass>
		<ns4:cusip>31620M106</ns4:cusip>
		<ns4:value>249894</ns4:value>
		<ns4:shrsOrPrnAmt>
			<ns4:sshPrnamt>3789711</ns4:sshPrnamt>
			<ns4:sshPrnamtType>SH</ns4:sshPrnamtType>
		</ns4:shrsOrPrnAmt>
		<ns4:investmentDiscretion>SOLE</ns4:investmentDiscretion>
		<ns4:votingAuthority>
			<ns4:Sole>3789711</ns4:Sole>
			<ns4:Shared>0</ns4:Shared>
			<ns4:None>0</ns4:None>
		</ns4:votingAuthority>
	</ns4:infoTable>
	<ns4:infoTable>
		<ns4:nameOfIssuer>FISERV INC</ns4:nameOfIssuer>
		<ns4:titleOfClass>COM</ns4:titleOfClass>
		<ns4:cusip>337738108</ns4:cusip>
		<ns4:value>115392</ns4:value>
		<ns4:shrsOrPrnAmt>
			<ns4:sshPrnamt>895000</ns4:sshPrnamt>
			<ns4:sshPrnamtType>SH</ns4:sshPrnamtType>
		</ns4:shrsOrPrnAmt>
		<ns4:investmentDiscretion>SOLE</ns4:investmentDiscretion>
		<ns4:votingAuthority>
			<ns4:Sole>895000</ns4:Sole>
			<ns4:Shared>0</ns4:Shared>
			<ns4:None>0</ns4:None>
		</ns4:votingAuthority>
	</ns4:infoTable>
	<ns4:infoTable>
		<ns4:nameOfIssuer>GDS HLDGS LTD</ns4:nameOfIssuer>
		<ns4:titleOfClass>SPONSORED ADS</ns4:titleOfClass>
		<ns4:cusip>36165L108</ns4:cusip>
		<ns4:value>125773</ns4:value>
		<ns4:shrsOrPrnAmt>
			<ns4:sshPrnamt>3249952</ns4:sshPrnamt>
			<ns4:sshPrnamtType>SH</ns4:sshPrnamtType>
		</ns4:shrsOrPrnAmt>
		<ns4:investmentDiscretion>SOLE</ns4:investmentDiscretion>
		<ns4:votingAuthority>
			<ns4:Sole>3249952</ns4:Sole>
			<ns4:Shared>0</ns4:Shared>
			<ns4:None>0</ns4:None>
		</ns4:votingAuthority>
	</ns4:infoTable>
	<ns4:infoTable>
		<ns4:nameOfIssuer>GENUINE PARTS CO</ns4:nameOfIssuer>
		<ns4:titleOfClass>COM</ns4:titleOfClass>
		<ns4:cusip>372460105</ns4:cusip>
		<ns4:value>193347</ns4:value>
		<ns4:shrsOrPrnAmt>
			<ns4:sshPrnamt>1395000</ns4:sshPrnamt>
			<ns4:sshPrnamtType>SH</ns4:sshPrnamtType>
		</ns4:shrsOrPrnAmt>
		<ns4:investmentDiscretion>SOLE</ns4:investmentDiscretion>
		<ns4:votingAuthority>
			<ns4:Sole>1395000</ns4:Sole>
			<ns4:Shared>0</ns4:Shared>
			<ns4:None>0</ns4:None>
		</ns4:votingAuthority>
	</ns4:infoTable>
	<ns4:infoTable>
		<ns4:nameOfIssuer>HERBALIFE LTD</ns4:nameOfIssuer>
		<ns4:titleOfClass>COM SHS</ns4:titleOfClass>
		<ns4:cusip>G4412G101</ns4:cusip>
		<ns4:value>65493</ns4:value>
		<ns4:shrsOrPrnAmt>
			<ns4:sshPrnamt>7759844</ns4:sshPrnamt>
			<ns4:sshPrnamtType>SH</ns4:sshPrnamtType>
		</ns4:shrsOrPrnAmt>
		<ns4:investmentDiscretion>SOLE</ns4:investmentDiscretion>
		<ns4:votingAuthority>
			<ns4:Sole>7759844</ns4:Sole>
			<ns4:Shared>0</ns4:Shared>
			<ns4:None>0</ns4:None>
		</ns4:votingAuthority>
	</ns4:infoTable>
	<ns4:infoTable>
		<ns4:nameOfIssuer>HERBALIFE LTD</ns4:nameOfIssuer>
		<ns4:titleOfClass>NOTE 4.250% 6/1</ns4:titleOfClass>
		<ns4:cusip>42703MAF0</ns4:cusip>
		<ns4:value>15833</ns4:value>
		<ns4:shrsOrPrnAmt>
			<ns4:sshPrnamt>17129000</ns4:sshPrnamt>
			<ns4:sshPrnamtType>PRN</ns4:sshPrnamtType>
		</ns4:shrsOrPrnAmt>
		<ns4:investmentDiscretion>SOLE</ns4:investmentDiscretion>
		<ns4:votingAuthority>
			<ns4:Sole>17129000</ns4:Sole>
			<ns4:Shared>0</ns4:Shared>
			<ns4:None>0</ns4:None>
		</ns4:votingAuthority>
	</ns4:infoTable>
	<ns4:infoTable>
		<ns4:nameOfIssuer>LIBERTY GLOBAL LTD</ns4:nameOfIssuer>
		<ns4:titleOfClass>COM CL A</ns4:titleOfClass>
		<ns4:cusip>G61188101</ns4:cusip>
		<ns4:value>58180</ns4:value>
		<ns4:shrsOrPrnAmt>
			<ns4:sshPrnamt>5076762</ns4:sshPrnamt>
			<ns4:sshPrnamtType>SH</ns4:sshPrnamtType>
		</ns4:shrsOrPrnAmt>
		<ns4:investmentDiscretion>SOLE</ns4:investmentDiscretion>
		<ns4:votingAuthority>
			<ns4:Sole>5076762</ns4:Sole>
			<ns4:Shared>0</ns4:Shared>
			<ns4:None>0</ns4:None>
		</ns4:votingAuthority>
	</ns4:infoTable>
	<ns4:infoTable>
		<ns4:nameOfIssuer>LIBERTY GLOBAL LTD</ns4:nameOfIssuer>
		<ns4:titleOfClass>COM CL C</ns4:titleOfClass>
		<ns4:cusip>G61188127</ns4:cusip>
		<ns4:value>254479</ns4:value>
		<ns4:shrsOrPrnAmt>
			<ns4:sshPrnamt>21657803</ns4:sshPrnamt>
			<ns4:sshPrnamtType>SH</ns4:sshPrnamtType>
		</ns4:shrsOrPrnAmt>
		<ns4:investmentDiscretion>SOLE</ns4:investmentDiscretion>
		<ns4:votingAuthority>
			<ns4:Sole>21657803</ns4:Sole>
			<ns4:Shared>0</ns4:Shared>
			<ns4:None>0</ns4:None>
		</ns4:votingAuthority>
	</ns4:infoTable>
	<ns4:infoTable>
		<ns4:nameOfIssuer>PAGSEGURO DIGITAL LTD</ns4:nameOfIssuer>
		<ns4:titleOfClass>COM CL A</ns4:titleOfClass>
		<ns4:cusip>G68707101</ns4:cusip>
		<ns4:value>25000</ns4:value>
		<ns4:shrsOrPrnAmt>
			<ns4:sshPrnamt>2500000</ns4:sshPrnamt>
			<ns4:sshPrnamtType>SH</ns4:sshPrnamtType>
		</ns4:shrsOrPrnAmt>
		<ns4:investmentDiscretion>SOLE</ns4:investmentDiscretion>
		<ns4:votingAuthority>
			<ns4:Sole>2500000</ns4:Sole>
			<ns4:Shared>0</ns4:Shared>
			<ns4:None>0</ns4:None>
		</ns4:votingAuthority>
	</ns4:infoTable>
	<ns4:infoTable>
		<ns4:nameOfIssuer>RESTAURANT BRANDS INTL INC</ns4:nameOfIssuer>
		<ns4:titleOfClass>COM</ns4:titleOfClass>
		<ns4:cusip>76131D103</ns4:cusip>
		<ns4:value>529337</ns4:value>
		<ns4:shrsOrPrnAmt>
			<ns4:sshPrnamt>8252862</ns4:sshPrnamt>
			<ns4:sshPrnamtType>SH</ns4:sshPrnamtType>
		</ns4:shrsOrPrnAmt>
		<ns4:investmentDiscretion>SOLE</ns4:investmentDiscretion>
		<ns4:votingAuthority>
			<ns4:Sole>8252862</ns4:Sole>
			<ns4:Shared>0</ns4:Shared>
			<ns4:None>0</ns4:None>
		</ns4:votingAuthority>
	</ns4:infoTable>
	<ns4:infoTable>
		<ns4:nameOfIssuer>TAMBORAN RES CORP</ns4:nameOfIssuer>
		<ns4:titleOfClass>COM</ns4:titleOfClass>
		<ns4:cusip>87507T101</ns4:cusip>
		<ns4:value>15629</ns4:value>
		<ns4:shrsOrPrnAmt>
			<ns4:sshPrnamt>570833</ns4:sshPrnamt>
			<ns4:sshPrnamtType>SH</ns4:sshPrnamtType>
		</ns4:shrsOrPrnAmt>
		<ns4:investmentDiscretion>SOLE</ns4:investmentDiscretion>
		<ns4:votingAuthority>
			<ns4:Sole>570833</ns4:Sole>
			<ns4:Shared>0</ns4:Shared>
			<ns4:None>0</ns4:None>
		</ns4:votingAuthority>
	</ns4:infoTable>
	<ns4:infoTable>
		<ns4:nameOfIssuer>UNION PAC CORP</ns4:nameOfIssuer>
		<ns4:titleOfClass>COM</ns4:titleOfClass>
		<ns4:cusip>907818108</ns4:cusip>
		<ns4:value>353658</ns4:value>
		<ns4:shrsOrPrnAmt>
			<ns4:sshPrnamt>1496204</ns4:sshPrnamt>
			<ns4:sshPrnamtType>SH</ns4:sshPrnamtType>
		</ns4:shrsOrPrnAmt>
		<ns4:investmentDiscretion>SOLE</ns4:investmentDiscretion>
		<ns4:votingAuthority>
			<ns4:Sole>1496204</ns4:Sole>
			<ns4:Shared>0</ns4:Shared>
			<ns4:None>0</ns4:None>
		</ns4:votingAuthority>
	</ns4:infoTable>
	<ns4:infoTable>
		<ns4:nameOfIssuer>WESCO INTL INC</ns4:nameOfIssuer>
		<ns4:titleOfClass>COM</ns4:titleOfClass>
		<ns4:cusip>95082P105</ns4:cusip>
		<ns4:value>317923</ns4:value>
		<ns4:shrsOrPrnAmt>
			<ns4:sshPrnamt>1503180</ns4:sshPrnamt>
			<ns4:sshPrnamtType>SH</ns4:sshPrnamtType>
		</ns4:shrsOrPrnAmt>
		<ns4:investmentDiscretion>SOLE</ns4:investmentDiscretion>
		<ns4:votingAuthority>
			<ns4:Sole>1503180</ns4:Sole>
			<ns4:Shared>0</ns4:Shared>
			<ns4:None>0</ns4:None>
		</ns4:votingAuthority>
	</ns4:infoTable>
	<ns4:infoTable>
		<ns4:nameOfIssuer>WILLIS TOWERS WATSON PLC LTD</ns4:nameOfIssuer>
		<ns4:titleOfClass>SHS</ns4:titleOfClass>
		<ns4:cusip>G96629103</ns4:cusip>
		<ns4:value>376218</ns4:value>
		<ns4:shrsOrPrnAmt>
			<ns4:sshPrnamt>1089065</ns4:sshPrnamt>
			<ns4:sshPrnamtType>SH</ns4:sshPrnamtType>
		</ns4:shrsOrPrnAmt>
		<ns4:investmentDiscretion>SOLE</ns4:investmentDiscretion>
		<ns4:votingAuthority>
			<ns4:Sole>1089065</ns4:Sole>
			<ns4:Shared>0</ns4:Shared>
			<ns4:None>0</ns4:None>
		</ns4:votingAuthority>
	</ns4:infoTable>
</ns4:informationTable>
